allsafe_auth/__init__.py
allsafe_auth/authentication/__init__.py
allsafe_auth/authentication/active_directory.py
allsafe_auth/authentication/google_authenticator.py
allsafe_auth/authentication/hotp.py
allsafe_auth/authentication/oauth2.py
allsafe_auth/authentication/saml.py
allsafe_auth/authentication/totp.py
allsafe_auth/mfa/__init__.py
allsafe_auth/mfa/backup_methods.py
allsafe_auth/mfa/mfa_manager.py
allsafe_auth/security/__init__.py
allsafe_auth/security/audit_logging.py
allsafe_auth/security/encryption.py
allsafe_auth/security/password_manager.py
allsafe_auth/security/session_manager.py
allsafe_auth/user_management/__init__.py
allsafe_auth/user_management/role_manager.py
allsafe_auth/user_management/user_manager.py
allsafe_auth/user_management/resolvers/__init__.py
allsafe_auth/user_management/resolvers/ldap_resolver.py
allsafe_auth/user_management/resolvers/mongodb_resolver.py
allsafe_auth/user_management/resolvers/mysql_resolver.py
allsafe_auth/user_management/resolvers/postgresql_resolver.py
allsafe_auth/user_management/resolvers/resolver_manager.py
allsafe_auth/utils/__init__.py
allsafe_auth/utils/config_loader.py
allsafe_auth/utils/qr_code_generator.py
allsafe_auth/utils/validators.py
tests/__init__.py
tests/list_users.py
tests/test_active_directory.py
tests/test_oauth2.py
tests/test_saml.py
tests/test_totp.py
tests/test_user_management.py
allsafe_authentication-0.0.1.dist-info/LICENSE
allsafe_authentication-0.0.1.dist-info/METADATA
allsafe_authentication-0.0.1.dist-info/WHEEL
allsafe_authentication-0.0.1.dist-info/top_level.txt
allsafe_authentication-0.0.1.dist-info/RECORD
