Metadata-Version: 2.1
Name: allsafe-authentication
Version: 0.0.1
Summary: A complete authentication library including TOTP, HOTP, Active Directory, and more.
Home-page: UNKNOWN
Author: Daniel Destaw
Author-email: daniel@allsafe.com
License: UNKNOWN
Platform: UNKNOWN
Classifier: Programming Language :: Python :: 3
Classifier: License :: OSI Approved :: MIT License
Classifier: Operating System :: OS Independent
Requires-Python: >=3.6
License-File: LICENSE
